pigcel/__init__.py
pigcel/__pkginfo__.py
pigcel/gui/__init__.py
pigcel/gui/dialogs/__init__.py
pigcel/gui/dialogs/group_averages_dialog.py
pigcel/gui/dialogs/group_effect_dialog.py
pigcel/gui/dialogs/group_medians_dialog.py
pigcel/gui/dialogs/time_effect_dialog.py
pigcel/gui/main_windows/__init__.py
pigcel/gui/main_windows/main_window.py
pigcel/gui/models/__init__.py
pigcel/gui/models/animals_data_model.py
pigcel/gui/models/animals_groups_model.py
pigcel/gui/models/animals_pool_model.py
pigcel/gui/models/exportable_data_model.py
pigcel/gui/models/pandas_data_model.py
pigcel/gui/models/pvalues_data_model.py
pigcel/gui/models/valid_times_model.py
pigcel/gui/models/workbook_data_model.py
pigcel/gui/utils/__init__.py
pigcel/gui/utils/navigation_toolbar.py
pigcel/gui/views/__init__.py
pigcel/gui/views/animals_data_listview.py
pigcel/gui/views/animals_groups_listview.py
pigcel/gui/views/animals_pool_listview.py
pigcel/gui/views/copy_pastable_tableview.py
pigcel/gui/views/double_clickable_listview.py
pigcel/gui/views/droppable_listview.py
pigcel/gui/widgets/__init__.py
pigcel/gui/widgets/groups_widget.py
pigcel/gui/widgets/logger_widget.py
pigcel/gui/widgets/multiple_directories_selector.py
pigcel/gui/widgets/plots_widget.py
pigcel/icons/export.ico
pigcel/icons/pigcel.icns
pigcel/icons/pigcel.png
pigcel/kernel/__init__.py
pigcel/kernel/readers/__init__.py
pigcel/kernel/readers/excel_reader.py
pigcel/kernel/utils/__init__.py
pigcel/kernel/utils/progress_bar.py
pigcel/kernel/utils/stats.py
pigcel/kernel/utils/time_io.py
pigcel-0.0.5.data/scripts/pigcel
pigcel-0.0.5.dist-info/LICENSE
pigcel-0.0.5.dist-info/METADATA
pigcel-0.0.5.dist-info/WHEEL
pigcel-0.0.5.dist-info/top_level.txt
pigcel-0.0.5.dist-info/RECORD
